stuboto.py
stuboto-0.3.dist-info/LICENSE
stuboto-0.3.dist-info/METADATA
stuboto-0.3.dist-info/WHEEL
stuboto-0.3.dist-info/top_level.txt
stuboto-0.3.dist-info/RECORD
