Metadata-Version: 2.1
Name: stuboto
Version: 0.3
Summary: Stub boto3 clients to avoid hitting real AWS endpoints in tests
Home-page: https://github.com/jmsanders/stuboto
Author: Jordan Sanders
Author-email: jordan@jordansanders.com
License: UNKNOWN
Platform: UNKNOWN
Classifier: Programming Language :: Python :: 3
Classifier: License :: OSI Approved :: MIT License
Classifier: Operating System :: OS Independent
Requires-Dist: boto3 (>=1.9.213)
